web2vec/__init__.py
web2vec/config.py
web2vec/utils.py
web2vec/version.py
web2vec/crawlers/__init__.py
web2vec/crawlers/extractors.py
web2vec/crawlers/models.py
web2vec/crawlers/spiders.py
web2vec/extractors/__init__.py
web2vec/extractors/dns_features.py
web2vec/extractors/html_body_features.py
web2vec/extractors/http_response_features.py
web2vec/extractors/network_features.py
web2vec/extractors/ssl_certification_features.py
web2vec/extractors/url_geo_features.py
web2vec/extractors/url_lexical_features.py
web2vec/extractors/whois_features.py
web2vec/extractors/external_api/__init__.py
web2vec/extractors/external_api/google_index_features.py
web2vec/extractors/external_api/open_pagerank_features.py
web2vec/extractors/external_api/open_phish_features.py
web2vec/extractors/external_api/phish_tank_features.py
web2vec/extractors/external_api/similar_web_features.py
web2vec/extractors/external_api/url_haus_features.py
web2vec-0.1.4.dist-info/licenses/LICENSE
web2vec-0.1.4.dist-info/METADATA
web2vec-0.1.4.dist-info/WHEEL
web2vec-0.1.4.dist-info/top_level.txt
web2vec-0.1.4.dist-info/RECORD
