Metadata-Version: 2.4
Name: web2vec
Version: 0.1.4
Summary: Website to vector representation library
Home-page: https://github.com/damianfraszczak/web2vec
Author: Damian Frąszczak, Edyta Frąszczak
Author-email: damian.fraszczak@wat.edu.pl
License: MIT
Keywords: website_processing crawling scraping web2vec
Classifier: Development Status :: 4 - Beta
Classifier: Intended Audience :: Developers
Classifier: Topic :: Software Development :: Build Tools
Classifier: License :: OSI Approved :: MIT License
Classifier: Programming Language :: Python
Classifier: Programming Language :: Python :: 3
License-File: LICENSE
Requires-Dist: scrapy
Requires-Dist: networkx
Requires-Dist: beautifulsoup4
Requires-Dist: matplotlib
Requires-Dist: scipy
Requires-Dist: python-whois
Requires-Dist: dnspython
Requires-Dist: geoip2
Requires-Dist: tldextract
Requires-Dist: selenium
Requires-Dist: webdriver-manager
Requires-Dist: dnspython
Requires-Dist: pydantic
Requires-Dist: pydantic_settings
Provides-Extra: lint
Requires-Dist: bandit; extra == "lint"
Requires-Dist: black; extra == "lint"
Requires-Dist: flake8; extra == "lint"
Requires-Dist: flake8-debugger; extra == "lint"
Requires-Dist: flake8-docstrings; extra == "lint"
Requires-Dist: flake8-isort; extra == "lint"
Requires-Dist: mypy; extra == "lint"
Requires-Dist: pylint; extra == "lint"
Dynamic: author
Dynamic: author-email
Dynamic: classifier
Dynamic: description
Dynamic: description-content-type
Dynamic: home-page
Dynamic: keywords
Dynamic: license
Dynamic: license-file
Dynamic: provides-extra
Dynamic: requires-dist
Dynamic: summary
